{
  "kind": "collectionType",
  "collectionName": "blog_entries",
  "info": {
    "singularName": "blog-entry",
    "pluralName": "blog-entries",
    "displayName": "Blog entry",
    "description": ""
  },
  "options": {
    "draftAndPublish": true
  },
  "pluginOptions": {},
  "attributes": {
    "title": {
      "type": "string",
      "required": true
    },
    "body": {
      "type": "richtext"
    },
    "media": {
      "allowedTypes": [
        "images",
        "files",
        "videos"
      ],
      "type": "media",
      "multiple": true
    }
  }
}
